ionoscloud_object_storage_management/__init__.py
ionoscloud_object_storage_management/api_client.py
ionoscloud_object_storage_management/api_response.py
ionoscloud_object_storage_management/configuration.py
ionoscloud_object_storage_management/exceptions.py
ionoscloud_object_storage_management/rest.py
ionoscloud_object_storage_management/api/__init__.py
ionoscloud_object_storage_management/api/accesskeys_api.py
ionoscloud_object_storage_management/api/regions_api.py
ionoscloud_object_storage_management/models/__init__.py
ionoscloud_object_storage_management/models/access_key.py
ionoscloud_object_storage_management/models/access_key_create.py
ionoscloud_object_storage_management/models/access_key_ensure.py
ionoscloud_object_storage_management/models/access_key_read.py
ionoscloud_object_storage_management/models/access_key_read_list.py
ionoscloud_object_storage_management/models/access_key_read_list_all_of.py
ionoscloud_object_storage_management/models/bucket.py
ionoscloud_object_storage_management/models/bucket_create.py
ionoscloud_object_storage_management/models/bucket_ensure.py
ionoscloud_object_storage_management/models/bucket_read.py
ionoscloud_object_storage_management/models/bucket_read_list.py
ionoscloud_object_storage_management/models/bucket_read_list_all_of.py
ionoscloud_object_storage_management/models/error.py
ionoscloud_object_storage_management/models/error_messages.py
ionoscloud_object_storage_management/models/links.py
ionoscloud_object_storage_management/models/metadata.py
ionoscloud_object_storage_management/models/metadata_with_status.py
ionoscloud_object_storage_management/models/metadata_with_status_all_of.py
ionoscloud_object_storage_management/models/metadata_with_supported_regions.py
ionoscloud_object_storage_management/models/metadata_with_supported_regions_all_of.py
ionoscloud_object_storage_management/models/pagination.py
ionoscloud_object_storage_management/models/region.py
ionoscloud_object_storage_management/models/region_capability.py
ionoscloud_object_storage_management-1.0.0.dist-info/LICENSE
ionoscloud_object_storage_management-1.0.0.dist-info/METADATA
ionoscloud_object_storage_management-1.0.0.dist-info/WHEEL
ionoscloud_object_storage_management-1.0.0.dist-info/top_level.txt
ionoscloud_object_storage_management-1.0.0.dist-info/RECORD
