Metadata-Version: 2.1
Name: ionoscloud-object-storage-management
Version: 1.0.0
Summary: Python SDK for the ionoscloud-object-storage-management API
Home-page: https://github.com/ionos-cloud/sdk-python-object-storage-management
Author: Ionos Cloud
Author-email: sdk@cloud.ionos.com
Keywords: OpenAPI,OpenAPI-Generator,IONOS Cloud - Object Storage Management API
Classifier: Natural Language :: English
Classifier: Environment :: Web Environment
Classifier: Intended Audience :: Developers
Classifier: License :: OSI Approved :: Apache Software License
Classifier: Operating System :: POSIX
Classifier: Programming Language :: Python
Classifier: Programming Language :: Python :: 3
Classifier: Topic :: Software Development :: Libraries :: Python Modules
Classifier: Topic :: Software Development :: Libraries :: Application Frameworks
Classifier: Topic :: Internet :: WWW/HTTP
License-File: LICENSE
Requires-Dist: certifi>=14.05.14
Requires-Dist: six>=1.10
Requires-Dist: python-dateutil>=2.5.3
Requires-Dist: setuptools>=21.0.0
Requires-Dist: urllib3>=1.15.1
Requires-Dist: asn1crypto>=1.5.1
Requires-Dist: pydantic<2,>=1.10.5
Requires-Dist: future; python_version <= "2.7"
